django_smb/__init__.py
django_smb/admin.py
django_smb/apps.py
django_smb/forms.py
django_smb/tests.py
django_smb/urls.py
django_smb/views.py
django_smb/migrations/0001_initial.py
django_smb/migrations/0002_auto_20181126_1125.py
django_smb/migrations/0003_auto_20181126_1224.py
django_smb/migrations/0004_auto_20181126_1435.py
django_smb/migrations/0005_remotepath_is_imported.py
django_smb/migrations/__init__.py
django_smb/models/__init__.py
django_smb/models/remote_location.py
django_smb/models/remote_path.py
django_smb/templates/django_smb/create_location.html
django_smb/templates/django_smb/list_locations.html
django_smb-0.1.0.dist-info/LICENSE
django_smb-0.1.0.dist-info/METADATA
django_smb-0.1.0.dist-info/WHEEL
django_smb-0.1.0.dist-info/top_level.txt
django_smb-0.1.0.dist-info/RECORD
