Metadata-Version: 2.1
Name: django-smb
Version: 0.1.0
Summary: A simple Django app to manage SMB locations (Windows Share directories).
Home-page: https://github.com/ZviBaratz/django_dicom
Author: Zvi Baratz
Author-email: z.baratz@gmail.com
License: MIT
Keywords: django smb windows share remote
Platform: UNKNOWN
Classifier: Environment :: Web Environment
Classifier: Framework :: Django
Classifier: Framework :: Django :: 2.1
Classifier: Intended Audience :: Developers
Classifier: License :: OSI Approved :: MIT License
Classifier: Operating System :: OS Independent
Classifier: Programming Language :: Python
Classifier: Programming Language :: Python :: 3.7
Requires-Dist: pysmb
Provides-Extra: dev
Requires-Dist: flake8 ; extra == 'dev'
Requires-Dist: yapf ; extra == 'dev'
Provides-Extra: test
Requires-Dist: pytest ; extra == 'test'
